[
    {
        "Key": "QuestList",
        "Value": {
            "entries": [
                {
                    "Key": "0",
                    "Value": {
                        "selected": false,
                        "data": {
                            "QuestID": {
                                "StringType": {
                                    "_string": "0",
                                    "InitValue": "0",
                                    "$type": "StringType"
                                }
                            },
                            "Name": {
                                "StringType": {
                                    "_string": "EasterlyEstate_Q_Main_Ch6_S6_Contraband_S1_Name",
                                    "InitValue": "EasterlyEstate_Q_Main_Ch6_S6_Contraband_S1_Name",
                                    "$type": "StringType"
                                }
                            },
                            "Description": {
                                "StringType": {
                                    "_string": "EasterlyEstate_Q_Main_Ch6_S6_Contraband_S1_Des",
                                    "InitValue": "EasterlyEstate_Q_Main_Ch6_S6_Contraband_S1_Des",
                                    "$type": "StringType"
                                }
                            },
                            "Demands": {
                                "StringListType": {
                                    "_lsstring": [
                                        "key_chap6_item5_1",
                                        "1"
                                    ],
                                    "InitValue": [
                                        "key_chap6_item5_1",
                                        "1"
                                    ],
                                    "$type": "StringListType"
                                }
                            },
                            "ItemRewards": {
                                "StringListType": {
                                    "_lsstring": [
                                        "key_chap6_item6",
                                        "1"
                                    ],
                                    "InitValue": [
                                        "key_chap6_item6",
                                        "1"
                                    ],
                                    "$type": "StringListType"
                                }
                            },
                            "IsDeduct": {
                                "BoolType": {
                                    "_bool": true,
                                    "InitValue": true,
                                    "$type": "BoolType"
                                }
                            },
                            "CompletedDialog": {
                                "StringType": {
                                    "_string": "Q_Main_Ch6_S6_Contraband_S1",
                                    "InitValue": "Q_Main_Ch6_S6_Contraband_S1",
                                    "$type": "StringType"
                                }
                            },
                            "ProceedType": {
                                "QuestProceedEnumType": {
                                    "questProceedType": "Transit",
                                    "$type": "QuestProceedEnumType"
                                }
                            }
                        }
                    }
                }
            ]
        }
    }
]